notte_mcp/__init__.py
notte_mcp/server.py
notte_mcp-1.8.3.dist-info/METADATA
notte_mcp-1.8.3.dist-info/WHEEL
notte_mcp-1.8.3.dist-info/RECORD
