Metadata-Version: 2.4
Name: notte-mcp
Version: 1.8.3
Summary: The MCP server for Notte
Author-email: Notte Team  <hello@notte.cc>
Requires-Python: >=3.11
Requires-Dist: mcp[cli]==1.6.0
Requires-Dist: notte-sdk==v1.8.3
Requires-Dist: python-dotenv>=1.0.1
